{"is_source_file": true, "format": "JavaScript", "description": "This file contains client-side API functions for a word game frontend, including functions to fetch game status and submit guesses using axios HTTP requests.", "external_files": ["axios"], "external_methods": ["axios.create", "http.get", "http.post"], "published": ["getDailyStatus", "submitGuess"], "classes": [], "methods": [{"name": "getDailyStatus()", "description": "Fetches the current daily game status from the backend server.", "scope": "", "scopeKind": ""}, {"name": "submitGuess(guess)", "description": "Submits a word guess to the backend and returns the server's response.", "scope": "", "scopeKind": ""}], "calls": ["axios.create", "http.get", "http.post"], "search-terms": ["client.js", "axios API", "fetch game status", "submit guess", "word game frontend API"], "state": 2, "file_id": 21, "knowledge_revision": 49, "git_revision": "", "ctags": [{"_type": "tag", "name": "API_BASE", "path": "/home/kavia/workspace/code-generation/daily-word-guess-833-843/word_game_frontend/src/api/client.js", "pattern": "/^const API_BASE = process.env.REACT_APP_API_BASE || 'http:\\/\\/localhost:3001';$/", "language": "JavaScript", "kind": "constant"}, {"_type": "tag", "name": "getDailyStatus", "path": "/home/kavia/workspace/code-generation/daily-word-guess-833-843/word_game_frontend/src/api/client.js", "pattern": "/^export async function getDailyStatus() {$/", "language": "JavaScript", "kind": "function", "signature": "()"}, {"_type": "tag", "name": "http", "path": "/home/kavia/workspace/code-generation/daily-word-guess-833-843/word_game_frontend/src/api/client.js", "pattern": "/^const http = axios.create({$/", "language": "JavaScript", "kind": "constant"}, {"_type": "tag", "name": "submitGuess", "path": "/home/kavia/workspace/code-generation/daily-word-guess-833-843/word_game_frontend/src/api/client.js", "pattern": "/^export async function submitGuess(guess) {$/", "language": "JavaScript", "kind": "function", "signature": "(guess)"}], "hash": "6ef43fd2832da791f8596f054c9bc1f8", "format-version": 4, "code-base-name": "word_game_frontend", "filename": "word_game_frontend/src/api/client.js", "revision_history": [{"49": ""}]}